src/mcp_server_sqlite/__init__.py
src/mcp_server_sqlite/server.py
mseep_mcp_server_sqlite-0.6.2.dist-info/METADATA
mseep_mcp_server_sqlite-0.6.2.dist-info/WHEEL
mseep_mcp_server_sqlite-0.6.2.dist-info/entry_points.txt
mseep_mcp_server_sqlite-0.6.2.dist-info/RECORD
