Metadata-Version: 2.4
Name: mseep-mcp-server-sqlite
Version: 0.6.2
Summary: A simple SQLite MCP server
Requires-Python: >=3.10
Requires-Dist: mcp>=1.0.0
